promptify/__init__.py
promptify/cli.py
promptify/agent/__init__.py
promptify/agent/graph.py
promptify/agent/node.py
promptify/agent/state.py
promptify/cli_supports/ConfigTUI.py
promptify/cli_supports/PromptifyTUI.py
promptify/cli_supports/__init__.py
promptify/cli_supports/help_content.py
promptify/core/__init__.py
promptify/core/formatter.py
promptify/core/service.py
promptify/core/validator.py
promptify/core/providerSelection/__init__.py
promptify/core/providerSelection/config.py
promptify/core/providerSelection/providers.py
promptify/prompt/CriticAgentPrompt.py
promptify/prompt/TriageAgentPrompt.py
promptify/prompt/__init__.py
promptify/prompt/expertAgentPrompt.py
promptify/prompt/promptSmith.py
promptify/utils/__init__.py
promptify/utils/errors.py
pfy-0.1.4.dist-info/METADATA
pfy-0.1.4.dist-info/WHEEL
pfy-0.1.4.dist-info/entry_points.txt
pfy-0.1.4.dist-info/top_level.txt
pfy-0.1.4.dist-info/RECORD
