Metadata-Version: 2.4
Name: pfy
Version: 0.1.4
Summary: AI-powered prompt engineering CLI with multi-agent system
Project-URL: Homepage, https://github.com/siva-netizen/Promptify
Project-URL: Repository, https://github.com/siva-netizen/Promptify
Requires-Python: >=3.10
Requires-Dist: python-dotenv>=1.0.0
Requires-Dist: langchain>=1.1.0
Requires-Dist: langchain-google-genai>=3.2.0
Requires-Dist: litellm>=1.80.5
Requires-Dist: pyfiglet>=1.0.4
Requires-Dist: pyperclip>=1.11.0
Requires-Dist: rich>=14.2.0
Requires-Dist: textual>=6.7.1
Requires-Dist: typer>=0.20.0
Requires-Dist: promptmasker>=0.0
